dazllm/__init__.py
dazllm/cli.py
dazllm/cli_base.py
dazllm/cli_base_test.py
dazllm/cli_test.py
dazllm/core.py
dazllm/core_test.py
dazllm/image_utils.py
dazllm/image_utils_test.py
dazllm/llm_anthropic.py
dazllm/llm_anthropic_test.py
dazllm/llm_claude_cli.py
dazllm/llm_claude_cli_test.py
dazllm/llm_cli_claude.py
dazllm/llm_cli_claude_test.py
dazllm/llm_cli_codex.py
dazllm/llm_cli_codex_test.py
dazllm/llm_cli_gemini.py
dazllm/llm_cli_gemini_test.py
dazllm/llm_codex_cli.py
dazllm/llm_codex_cli_test.py
dazllm/llm_gemini_cli.py
dazllm/llm_gemini_cli_test.py
dazllm/llm_google.py
dazllm/llm_google_test.py
dazllm/llm_lmstudio.py
dazllm/llm_lmstudio_test.py
dazllm/llm_ollama.py
dazllm/llm_ollama_test.py
dazllm/llm_openai.py
dazllm/llm_openai_test.py
dazllm/memoization.py
dazllm/memoization_test.py
dazllm/model_resolver.py
dazllm/model_resolver_test.py
dazllm/provider_manager.py
dazllm/provider_manager_test.py
dazllm-0.39.0.dist-info/licenses/LICENSE
dazllm-0.39.0.dist-info/METADATA
dazllm-0.39.0.dist-info/WHEEL
dazllm-0.39.0.dist-info/entry_points.txt
dazllm-0.39.0.dist-info/top_level.txt
dazllm-0.39.0.dist-info/RECORD
