Metadata-Version: 2.4
Name: dazllm
Version: 0.39.0
Summary: Simple, unified interface for all major LLMs
Home-page: https://github.com/darrenoakey/dazllm
Author: Darren Oakey
Author-email: Darren Oakey <darren.oakey@insidemind.com.au>
License: MIT
Project-URL: Homepage, https://github.com/darrenoakey/dazllm
Project-URL: Documentation, https://github.com/darrenoakey/dazllm#readme
Project-URL: Repository, https://github.com/darrenoakey/dazllm.git
Project-URL: Bug Reports, https://github.com/darrenoakey/dazllm/issues
Keywords: llm,ai,openai,anthropic,claude,gemini,ollama,chatgpt,gpt-4
Classifier: Development Status :: 3 - Alpha
Classifier: Intended Audience :: Developers
Classifier: License :: OSI Approved :: MIT License
Classifier: Operating System :: OS Independent
Classifier: Programming Language :: Python :: 3
Classifier: Programming Language :: Python :: 3.8
Classifier: Programming Language :: Python :: 3.9
Classifier: Programming Language :: Python :: 3.10
Classifier: Programming Language :: Python :: 3.11
Classifier: Programming Language :: Python :: 3.12
Classifier: Topic :: Software Development :: Libraries :: Python Modules
Classifier: Topic :: Scientific/Engineering :: Artificial Intelligence
Requires-Python: >=3.8
License-File: LICENSE
Requires-Dist: keyring>=24.0.0
Requires-Dist: requests>=2.25.0
Requires-Dist: colorama>=0.4.0
Requires-Dist: pydantic>=2.0.0
Requires-Dist: jsonschema>=4.0.0
Requires-Dist: Pillow>=9.0.0
Requires-Dist: openai>=1.0.0
Requires-Dist: anthropic>=0.3.0
Requires-Dist: google-generativeai>=0.3.0
Requires-Dist: google-ai-generativelanguage
Provides-Extra: dev
Requires-Dist: pytest>=7.0.0; extra == "dev"
Requires-Dist: black>=22.0.0; extra == "dev"
Requires-Dist: flake8>=4.0.0; extra == "dev"
Requires-Dist: mypy>=0.950; extra == "dev"
Dynamic: author
Dynamic: home-page
Dynamic: license-file
Dynamic: requires-python
